build
dist
hoof
hoof_examples
tests
