Metadata-Version: 1.0
Name: hoof
Version: 0.0.2
Summary: Generate abstract syntax trees using antlr grammars
Home-page: https://github.com/machow/hoof
Author: Michael Chow
Author-email: mc_al_github@fastmail.com
License: UNKNOWN
Platform: UNKNOWN
